README.rst
setup.py
pyhpecfm/__init__.py
pyhpecfm/client.py
pyhpecfm/fabric.py
pyhpecfm/system.py
pyhpecfm.egg-info/PKG-INFO
pyhpecfm.egg-info/SOURCES.txt
pyhpecfm.egg-info/dependency_links.txt
pyhpecfm.egg-info/entry_points.txt
pyhpecfm.egg-info/requires.txt
pyhpecfm.egg-info/top_level.txt
pyhpecfm/integrations/__init__.py
pyhpecfm/integrations/kubernetes.py
pyhpecfm/integrations/nsx.py
pyhpecfm/integrations/simplivity.py