Metadata-Version: 1.1
Name: pyhpecfm
Version: 0.1.5
Summary: Python binding for HPE Composable Fabric Manager
Home-page: https://github.com/hewlettpackard
Author: bri365
Author-email: brian.j.martin@hpe.com
License: Apache2
Keywords: plexxi,composable fabric manager,cfm,composable cloud
Platform: UNKNOWN
Classifier: Development Status :: 3 - Alpha
Classifier: Intended Audience :: Developers
Classifier: Intended Audience :: System Administrators
Classifier: License :: OSI Approved :: Apache Software License
Classifier: Programming Language :: Python
Classifier: Natural Language :: English
Classifier: Operating System :: OS Independent
Classifier: Topic :: Software Development :: Libraries :: Python Modules
